<?xml version="1.0" encoding="UTF-8"?>
<play xmlns:tei="http://www.tei-c.org/ns/1.0" name="Henry_IV,_Part_2">
   <w n="5">sherris</w>
   <w n="2">foutre</w>
   <w n="1">juvenal</w>
   <w n="1">continuantly</w>
   <w n="1">exion</w>
   <w n="1">fustilarian</w>
   <w n="1">keech</w>
   <w n="1">sneap</w>
   <w n="1">drollery</w>
   <w n="1">persistency</w>
   <w n="1">tardily</w>
   <w n="1">temperality</w>
   <w n="1">pulsidge</w>
   <w n="1">undeserver</w>
   <w n="1">sortance</w>
   <w n="1">fangless</w>
   <w n="1">forgetive</w>
   <w n="1">unfathered</w>
   <w n="1">correctioner</w>
</play>
